src/__init__.py
src/cli.py
src/utils.py
src/tes/__init__.py
src/tes/tes_client.py
ga4gh_cli-0.1.9.dist-info/LICENSE
ga4gh_cli-0.1.9.dist-info/METADATA
ga4gh_cli-0.1.9.dist-info/WHEEL
ga4gh_cli-0.1.9.dist-info/entry_points.txt
ga4gh_cli-0.1.9.dist-info/top_level.txt
ga4gh_cli-0.1.9.dist-info/RECORD
